{"autoSearch":true,"img":"https://image.tmdb.org/t/p/w600_and_h900_bestv2/walhhrMr5rKSpXo1c5MuC3ZM0x9.jpg","imdb":"129139","servers":["https://www.pelisplay.co/pelicula/cosas-que-hacer-antes-de-los-18","https://allcalidad.la/cosas-que-hacer-antes-de-los-18/","https://cinetux.nu/pelicula/ver-the-to-do-list-online/","https://www.pelisxd.com/pelicula/cosas-que-hacer-antes-de-los-18/"],"isSaved":true,"release":"2013/07/24","genero":"Comedia ","titulo":"Cosas que hacer antes de los 18","_id":{"$oid":"5bc7d0c95d0e651b2e58cc8b"},"año":"2013/07/26","sinopsis":"La pelicula comienza cuando una prometedora joven se acaba de graduar satisfactoriamente en el instituto con unas buenas notas, pero eso no es suficiente. Novata en temas sexuales, decide confeccionar una lista con todo lo que quiere probar y experimentar, y se propone cumplir todos y cada uno de sus apartados antes de entrar en la universidad. Explotando su feminidad tanto como las circunstancias se lo permiten, contará con el asesoramiento de sus amigas. Incorrecta y disparatada, está cómica historia recorre asuntos familiares, primeras experiencias, y sobretodo el desmelenarse de una chica sin vergüenza ni pudor, con mucha imaginación y ganas de sentir."}