{"autoSearch":true,"img":"https://image.tmdb.org/t/p/w600_and_h900_bestv2/mc9b25IAprHfsaOz0wTshOwGHcY.jpg","imdb":"14869","servers":["https://www.pelisplay.co/pelicula/g-i-joe-1","https://allcalidad.la/g-i-joe-origen-cobra/","https://pelisap.com/g-i-joe-el-origen-de-cobra/","https://www.aquipelis.info/pelicula/g-i-joe-origen-cobra/","https://cinetux.nu/pelicula/ver-pelicula-gi-joe-online-gratis-2009/","https://fanpelis.net/g-joe-el-origen-de-cobra/","https://pelisplus.video/pelicula/g-i-joe-el-origen-de-cobra","https://www.pelisxd.com/pelicula/g-i-joe/","https://www.pelispedia.pro/pelicula/g-i-joe/","https://repelisgoo.org/pelicula/gi-joe-the-rise-of-cobra-OxSak"],"isSaved":true,"release":"2009/08/04","genero":"acción Aventura ","titulo":"G.I. Joe","_id":{"$oid":"5bc7d08a1f6e4f34af69f175"},"año":"2009/08/7","sinopsis":"G. I. Joe es el nombre en clave de una fuerza especial altamente entrenada cuya misio?n fundamental es defender la libertad humana y la paz mundial. Los valerosos Joes son hombres y mujeres de coraje, duen?os de una mezcla dina?mica de talentos especiales, personalidad e ingenuidad. Dotados de algunas de las armas ma?s sofisticadas que puedan concebirse, estos individuos constituyen la fuerza ma?s formidable de combate del mundo."}