{"autoSearch":true,"img":"https://image.tmdb.org/t/p/w600_and_h900_bestv2/pJdeBkyHCkig46UqR5pCs3ACUFu.jpg","imdb":"162903","servers":["https://www.pelisplay.co/pelicula/el-quinto-poder","https://allcalidad.la/el-quinto-poder/","https://pelisap.com/el-quinto-poder/","https://cinetux.nu/pelicula/ver-el-quinto-poder-the-fifth-estate-online/","https://www.repelisplus.vip/ver/el-quinto-poder/","https://fanpelis.net/el-quinto-poder/","https://pelisplus.video/pelicula/el-quinto-poder","https://www.pelisxd.com/pelicula/el-quinto-poder/","https://www.pelispedia.mobi/pelicula/el-quinto-poder/"],"isSaved":true,"release":"2013/10/11","genero":"Drama Thriller ","titulo":"El quinto poder","_id":{"$oid":"5bc7d0ee1f6e4f34af69f2d8"},"año":"2013/10/18","sinopsis":"Julian Assange y Daniel Domscheit-Berg crean WikiLeaks, una plataforma que permite denunciar de forma anónima y filtrar información secreta, iluminando los oscuros recovecos de los secretos gubernamentales y crímenes corporativos. No tardan en revelar más noticias que todas las organizaciones de comunicación más prestigiosas del mundo juntas. Pero cuando Assange y Berg obtienen acceso a la mayor cantidad de documentos confidenciales de la historia de los servicios de inteligencia de los Estados Unidos, se enfrentan a una de las cuestiones claves de nuestro tiempo: ¿cuál es el coste de guardar secretos en una sociedad libre y cuál es el coste de exponerlos?"}