{"autoSearch":true,"img":"https://image.tmdb.org/t/p/w600_and_h900_bestv2/tE9lFSCecv60Rl1DNUMj3urTxda.jpg","imdb":"16290","servers":["https://www.pelisplay.co/pelicula/jackass-3d","https://allcalidad.la/jackass-3d/","https://cinetux.nu/pelicula/ver-pelicula-jackass-3d-online-gratis-2010/","https://www.repelisplus.vip/ver/jackass-3d/","https://fanpelis.net/jackass-3d/","https://pelisplus.video/pelicula/jackass-3d","https://www.pelisxd.com/pelicula/jackass-3d/","https://www.pelispedia.pro/pelicula/jackass-3d/"],"isSaved":true,"release":"2010/10/15","genero":"acción Comedia Documental ","titulo":"Jackass 3D","_id":{"$oid":"5bc7d0551f6e4f34af69f0e4"},"año":"2010/10/15","sinopsis":"El formato Jackass, donde Johnny Knoxville y sus amigos se someten al peligro de forma voluntaria, se adapta al cine 3D. En su primera semana en USA ha obtenido un enorme éxito de taquilla: nada menos que 50 millones de dólares, la película con mejor entrada del otoño 2010."}