{"autoSearch":true,"img":"https://image.tmdb.org/t/p/w600_and_h900_bestv2/5SbIDk0Gkyr0y22ZtydVq9Px423.jpg","imdb":"201085","servers":["https://www.pelisplay.co/pelicula/la-cumbre-escarlata","https://allcalidad.la/la-cumbre-escarlata/","https://pelisap.com/la-cumbre-escarlata/","https://pelisplusgo.com/pelicula/crimson-peak-4OHnl","https://cinetux.nu/pelicula/ver-la-cumbre-escarlata-crimson-peak-online/","https://www.repelisplus.vip/ver/la-cumbre-escarlata-g/","https://fanpelis.net/la-cumbre-escarlata/","https://pelisplus.video/pelicula/la-cumbre-escarlata","https://www.pelisxd.com/pelicula/la-cumbre-escarlata/","https://www.pelispedia.mobi/pelicula/la-cumbre-escarlata/","https://repelisgoo.net/pelicula/crimson-peak-x0fzp"],"isSaved":true,"release":"2015/10/13","genero":"Drama Fantasia ","titulo":"La cumbre escarlata","_id":{"$oid":"5bc7d09f1f6e4f34af69f1ba"},"año":"2015/10/16","sinopsis":"Como consecuencia de una tragedia familiar, una escritora es incapaz de elegir entre el amor de su amigo de la infancia y la tentación que representa un misterioso desconocido. En un intento por escapar de los fantasmas del pasado, se encuentra de pronto en una casa que respira, sangra\u2026 y recuerda."}