{"autoSearch":true,"img":"https://image.tmdb.org/t/p/w600_and_h900_bestv2/nbojNXZKLRrfbEOvvqssaiXqcdv.jpg","imdb":"228165","servers":["https://www.pelisplay.co/pelicula/bob-esponja-un-heroe-fuera-del-agua","https://allcalidad.la/bob-esponja-heroe-del-agua/","https://pelisap.com/bob-esponja-heroe-del-agua/","https://pelisplusgo.com/pelicula/the-spongebob-movie-sponge-out-of-water-WpHQp","https://cinetux.nu/pelicula/ver-pelicula-bob-esponja-un-heroe-fuera-del-agua-online-2015-gratis/","https://www.repelisplus.vip/ver/bob-esponja-un-heroe-fuera-del-agua/","https://fanpelis.net/bob-esponja-un-heroe-fuera-del-agua/","https://pelisplus.video/pelicula/bob-esponja-un-heroe-fuera-del-agua","https://www.pelisxd.com/pelicula/bob-esponja-un-heroe-fuera-del-agua/","https://repelisgoo.net/pelicula/the-spongebob-movie-sponge-out-of-water-DDsl9"],"isSaved":true,"release":"2015/01/28","genero":"animación Aventura Comedia ","titulo":"Bob Esponja: Un héroe fuera del agua","_id":{"$oid":"5bc7d0c11f6e4f34af69f242"},"año":"2015/03/27","sinopsis":"Segunda película sobre el personaje marino más querido por niños y adultos, Bob Esponja.\r El argumento gira en torno a Bob Esponja y sus inseparables amigos del mar, como son Patricio y la ardilla Arenita, y otros personajes de la serie en la que se basa, como Calamardo y Don Cangrejo. En esta ocasión Bob Esponja y cía se embarcan en una aventura en la que deberán encontrar una receta robada, lo que llevará a los personajes de Fondo Bikini hasta nuestra dimensión. Por lo que la película mezcla animación y escenas de acción real. Las escenas de animación están hechas tanto con CGI (imagen generada por ordenador) como en dibujo a mano.\r En la dimensión real se tendrán que enfrentar al pirata Alameda Jack, al que da vida Antonio Banderas."}