{"autoSearch":true,"img":"https://image.tmdb.org/t/p/w600_and_h900_bestv2/4GtFVW8MIx6DQ1p7FmXbEMSWwzd.jpg","imdb":"24420","servers":["https://allcalidad.la/te-amare-siempre/","https://pelisplusgo.com/pelicula/the-time-travelers-wife-p1Upr0","https://cinetux.nu/pelicula/ver-te-amare-por-siempre-online-gratis-2010/","https://www.repelisplus.vip/ver/te-amare-por-siempre/","https://fanpelis.net/te-amare-por-siempre/","https://pelisplus.video/pelicula/te-amare-por-siempre","https://repelisgoo.org/pelicula/the-time-travelers-wife-ARS49","https://www.pelisplay.co/pelicula/mas-alla-del-tiempo","http://verpelisonline.tv/ciencia-ficcion/11137-mas-alla-del-tiempo.html"],"isSaved":true,"release":"2009/08/14","genero":"Drama Fantasia Romance ","titulo":"Más allá del tiempo","_id":{"$oid":"5bc7d07a5d0e651b2e58cb4d"},"año":"2009/08/14","sinopsis":"Clare (Rachel McAdams) ha estado siempre enamorada de Henry (Eric Bana), un bibliotecario de Chicago. Está convencida de que están destinados a vivir juntos, aunque no sepa cuándo tendrán que volver a separarse: Henry es un viajero del tiempo, con una rara anomalía genética que lo condena a vivir su vida en una escala de tiempo cambiante, avanzando y retrocediendo a través de los años sin ningún control. A pesar de que los viajes de Henry son tan imprevisibles que Clare nunca sabe cuándo volverán a verse, intenta desesperadamente adaptarse a esa vida, pues lo que sí sabe es que no podría vivir sin Henry."}