{"autoSearch":true,"img":"https://image.tmdb.org/t/p/w600_and_h900_bestv2/pMJ8G2d1G6GhJjeZF8S6XoTdrXA.jpg","imdb":"244772","servers":["https://www.pelisplay.co/pelicula/the-skeleton-twins","https://allcalidad.la/los-gemelos-esqueleto/","https://cinetux.nu/pelicula/ver-pelicula-the-skeleton-twins-online-gratis-2014/","https://www.repelisplus.vip/ver/the-skeleton-twins/","https://fanpelis.net/the-skeleton-twins/","https://pelisplus.video/pelicula/the-skeleton-twins","https://www.pelisxd.com/pelicula/the-skeleton-twins/","https://www.pelispedia.mobi/pelicula/the-skeleton-twins/"],"isSaved":true,"release":"2014/09/12","genero":"Comedia Drama ","titulo":"The Skeleton Twins","_id":{"$oid":"5bc7d0745d0e651b2e58cb39"},"año":"2014/11/7","sinopsis":"Después de eludir la muerte el mismo día, los distanciados gemelos Milo y Maggie se reúnen para encontrar una explicación razonable del negativo rumbo de sus vidas."}