{"autoSearch":true,"img":"https://image.tmdb.org/t/p/w600_and_h900_bestv2/gxATKMGXgLm0jhI4ccQt4IAvaJq.jpg","imdb":"254474","servers":["https://www.pelisplay.co/pelicula/castores-zombies","https://allcalidad.la/castores-zombies/","https://allpeliculas.io/pelicula/Zombeavers","https://cinetux.nu/pelicula/ver-pelicula-castores-zombies-online-gratis-2014/","https://fanpelis.net/zombeavers-castores-zombies/","https://pelisplus.video/pelicula/castores-zombies","https://www.pelisxd.com/pelicula/zombeavers-castores-zombies/","https://www.repelisplus.vip/ver/castores-zombies-ae/"],"isSaved":true,"release":"2014/10/20","genero":"Comedia terror ","titulo":"Zombeavers (Castores zombies)","_id":{"$oid":"5bc7d0ae1f6e4f34af69f1ec"},"año":"2015/03/20","sinopsis":"Un grupo de jóvenes pretende pasar un fin de semana de diversión, alcohol y sexo. Sin embargo, su plan de diversión se truncará al cruzarse en su camino un grupo de castores zombis que tratará de acabar con ellos."}