{"autoSearch":true,"img":"https://image.tmdb.org/t/p/w600_and_h900_bestv2/cAQRgMxyuy3qhjCitR0hHJhEPAI.jpg","imdb":"268896","servers":["https://www.pelisplay.tv/pelicula/pacific-rim-insurreccion","https://www.inkapelis.tv/ver-pelicula-pacific-rim-2-insurreccion/","https://allcalidad.net/titanes-del-pacifico-la-insurreccion/","https://allpeliculas.io/pelicula/Titanes-del-Pacifico--La-insurreccion","https://www.aquipelis.co/pelicula/pacific-rim-2-insurreccion/"],"isSaved":true,"release":"2018/03/21","genero":"acción Aventura ","titulo":"Pacific Rim: Insurrección","_id":{"$oid":"5bc7cf681f6e4f34af69ed54"},"año":"2018/03/23","sinopsis":"Titanes del Pacífico: La insurrección Un futuro cercano. Después de la primera invasión que sufrió la humanidad, la lucha aún no ha terminado. El planeta vuelve a ser asediado por los Kaiju, una raza de alienígenas colosales que emergen desde un portal interdimensional, con el objetivo de destruir a la raza humana. Ante esta nueva amenaza para la cual los humanos no están preparados, los Jaegers, robots gigantes de guerra pilotados por dos personas para sobrellevar la inmensa carga neural que conlleva manipularlos, ya no están a la altura de lo que se les viene encima. Será entonces cuando los supervivientes de la primera invasión, además de nuevos personajes como el hijo de Pentecost (John Boyega), tendrán que idear la manera de sorprender al enorme enemigo, apostando por nuevas estrategias defensivas y de ataque. Con la Tierra en ruinas e intentando reconstruirse, esta nueva batalla puede ser decisiva para el futuro."}