{"autoSearch":true,"img":"https://image.tmdb.org/t/p/w600_and_h900_bestv2/bmWSCkItpRW2DkSwPKakyr0DNNw.jpg","imdb":"297806","servers":["https://allcalidad.la/la-historia-hank-williams/","https://pelisplusgo.com/pelicula/i-saw-the-light-bVHrO","https://cinetux.nu/pelicula/ver-i-saw-the-light-online/","https://www.repelisplus.vip/ver/i-saw-the-light/","https://fanpelis.net/la-historia-de-hank-williams/","https://www.pelisxd.com/pelicula/hank-williams-una-voz-a-la-deriva/","https://www.pelispedia.mobi/pelicula/hank-williams-una-voz-a-la-deriva/","https://repelisgoo.net/pelicula/i-saw-the-light-o3ikD"],"isSaved":true,"release":"2016/02/05","genero":"Drama Musica ","titulo":"Hank Williams, una voz a la deriva","_id":{"$oid":"5bc7d0165d0e651b2e58ca4e"},"año":"2016/04/1","sinopsis":"Biografía del músico y leyenda del country Hank Williams, desde sus orígenes humildes hasta su ascenso al estrellato, algo que le repercutiría de forma directa en su salud y vida personal."}