{"autoSearch":true,"img":"https://image.tmdb.org/t/p/w600_and_h900_bestv2/zGY41KlplvdPcUT0OeTu04ZPHke.jpg","imdb":"309581","servers":["https://www.pelisplay.co/pelicula/angel-de-venganza","https://allcalidad.la/angel-de-venganza/","https://cinetux.nu/pelicula/ver-pelicula-angel-de-venganza-angel-de-venganza-lila-eve-online-gratis-2015/","https://www.repelisplus.vip/ver/angel-de-venganza/","https://fanpelis.net/angel-de-venganza/","https://pelisplus.video/pelicula/angel-de-venganza","https://www.pelisxd.com/pelicula/angel-de-venganza/","https://www.pelispedia.mobi/pelicula/angel-de-venganza/"],"isSaved":true,"release":"2015/07/31","genero":"acción Crimen Drama ","titulo":"Ángel de venganza","_id":{"$oid":"5bc7d0ae1f6e4f34af69f1ed"},"año":"2015/07/17","sinopsis":"Lila y Eve, dos madres destrozadas por el asesinato de sus hijos, unen fuerzas para vengarse de los traficantes de droga responsables de la muerte del hijo de la primera. Pero a medida que la violencia crece, Lila empieza a descubrir la inquietante verdad sobre la verdadera identidad de Eve."}