{"autoSearch":true,"img":"https://image.tmdb.org/t/p/w600_and_h900_bestv2/cHdn5K9yM3GMur2zxdvLfstrWNA.jpg","imdb":"328387","servers":["https://www.pelisplay.tv/pelicula/nerve-un-juego-sin-reglas","https://www.inkapelis.tv/nerve-un-juego-sin-reglas/","https://allcalidad.net/nerve-un-juego-sin-reglas/","https://allpeliculas.io/pelicula/Un-juego-sin-reglas-Nerve","https://pelisgratis.live/nerve-juego-sin-reglas/","https://www.rexpelis.com/pelicula/nerve-un-juego-sin-reglas","https://www.aquipelis.co/pelicula/ver-nerve-juego-sin-reglas/"],"isSaved":true,"release":"2016/06/27","genero":"acción ","titulo":"Nerve: Un juego sin reglas","_id":{"$oid":"5bc7d00a5d0e651b2e58ca26"},"año":"2016/08/12","sinopsis":"Vee Delmonico es una joven y tímida estudiante de secundaria que decide apuntarse a Nerve, un provocativo juego online de 'verdad o acción' en el que la audiencia observa todo, vota y además comenta. Al principio logra mucho éxito y disfruta la situación, sobre todo gracias a los premios que ofrece el juego. Así, empieza a competir junto a un misterioso extraño (Dave Franco), que será su compañero de equipo. Pero, a medida que sube niveles, Nerve evoluciona y Vee se verá envuelta en un juego cada vez mas peligroso..."}