{"autoSearch":true,"img":"https://image.tmdb.org/t/p/w600_and_h900_bestv2/yGuQcsEmEkpgMbM6kLR4LrXOcfk.jpg","imdb":"359940","servers":["https://www.pelisplay.tv/pelicula/tres-anuncios-en-las-afueras","https://www.inkapelis.tv/tres-anuncios-en-las-afueras/","https://allcalidad.net/tres-anuncios-por-un-crimen/","https://pelisgratis.live/tres-anuncios-crimen-a/","https://www.rexpelis.com/pelicula/tres-anuncios-en-las-afueras","https://www.aquipelis.co/pelicula/ver-tres-anuncios-en-las-afueras-gratis/"],"isSaved":true,"release":"2017/11/10","genero":"Crimen Drama ","titulo":"Tres anuncios en las afueras","_id":{"$oid":"5bc7cf7e5d0e651b2e58c849"},"año":"2018/01/12","sinopsis":"Tres anuncios por un crimen En Ebbing, Misuri, un pueblo del Medio Oeste de Estados Unidos, Mildred Hayes (Frances McDormand) decide gastarse todos sus ahorros en contratar tres vallas publicitarias para poner en evidencia la incompetencia de la policía. Han pasado ya varios meses desde la violación y asesinato de su hija y aún no se sabe nada acerca de lo ocurrido. Estas tres vallas a la entrada del pueblo, con mensajes muy controvertidos sobre el jefe de policía, William Willoughby (Woody Harrelson), servirán para divulgar un recordatorio, el de un crimen sin resolver, y constatar una evidencia, que nadie ha sido detenido. Las consecuencias serán una guerra abierta contra la policía del pueblo, y una agria respuesta por parte de sus habitantes."}