{"autoSearch":true,"img":"https://image.tmdb.org/t/p/w600_and_h900_bestv2/hLXDrsgBqdO0xJHoRlBBMMortWL.jpg","imdb":"369972","servers":["https://www.pelisplay.tv/pelicula/ver--first-man-el-primer-hombre-hd-online","https://www.inkapelis.tv/first-man-el-primer-hombre-pelicula-completa-online/","https://allpeliculas.io/pelicula/El-primer-hombre-en-la-Luna","https://pelisgratis.live/first-man-el-primer-hombre-b/","https://www.rexpelis.com/pelicula/el-primer-hombre-first-man","https://www.aquipelis.co/pelicula/first-man-el-primer-hombre/"],"isSaved":true,"release":"2018/10/11","genero":"Drama","titulo":"First Man (El primer hombre)","_id":{"$oid":"5bc7d0875d0e651b2e58cb84"},"año":"2019/01/11","sinopsis":"Cuenta la historia de la misión de la NASA que llevó al primer hombre a la luna, centrada en Neil Armstrong y el periodo comprendido entre los años 1961 y 1969. Un relato en primera persona, basado en la novela de James R. Hansen, que explora el sacrificio y el precio que representó, tanto para Armstrong como para Estados Unidos, una de las misiones más peligrosas de la historia."}