{"autoSearch":true,"img":"https://image.tmdb.org/t/p/w600_and_h900_bestv2/nLIDouFvreSrs8xK62zuvpEPDw0.jpg","imdb":"376134","servers":["https://www.pelisplay.tv/pelicula/the-discovery","https://www.inkapelis.tv/the-discovery/","https://allpeliculas.io/pelicula/The-Discovery","https://www.rexpelis.com/pelicula/the-discovery","https://www.aquipelis.co/pelicula/the-discovery/"],"isSaved":true,"release":"2017/03/31","genero":"Drama Misterio Romance ","titulo":"The Discovery","_id":{"$oid":"5bc7cfea1f6e4f34af69efad"},"año":"2017/03/31","sinopsis":"En un futuro, tras demostrarse científicamente que hay vida después de la muerte, millones de personas de todo el mundo se suicidan para pasar a la otra vida. Un hombre y una mujer se enamoran mientras tratan de asimilar sus trágicos pasados y la verdadera naturaleza del más allá."}