{"autoSearch":true,"img":"https://image.tmdb.org/t/p/w600_and_h900_bestv2/98L63uVsv71kFWeM4ECdQ0Ko44a.jpg","imdb":"39514","servers":["https://www.pelisplay.co/pelicula/red","https://allcalidad.la/red/","https://allpeliculas.io/pelicula/RED","https://pelisap.com/red-1/","https://cinetux.nu/pelicula/ver-pelicula-red-online-gratis-2010/","https://www.repelisplus.vip/ver/red-retirados-extremadamente-duros/","https://fanpelis.net/red-retirados-extremadamente-duros/"],"isSaved":true,"release":"2010/10/13","genero":"acción Comedia Crimen ","titulo":"RED","_id":{"$oid":"5bc7d03b1f6e4f34af69f0a3"},"año":"2010/10/15","sinopsis":"Frank (Bruce Willis), Joe (Morgan Freeman), Marvin (John Malkovich) y Victoria (Helen Mirren) son agentes especiales ya retirados, a los que la nueva administración de Washington desea ver muertos. El motivo: eran los mejores agentes de la CIA, pero saben demasiado. Adaptación del cómic de Warren Ellis."}