{"autoSearch":true,"img":"https://image.tmdb.org/t/p/w600_and_h900_bestv2/bOYo3VZS0ELXgkZPyexXB3GIE64.jpg","imdb":"434555","servers":["https://www.pelisplay.tv/pelicula/ver-cadaver","https://www.inkapelis.tv/cadaver/","https://allcalidad.net/cadaver/","https://pelisgratis.live/cadaver-l/","https://www.rexpelis.com/pelicula/cadaver-2018","https://www.aquipelis.co/pelicula/cadaver/"],"isSaved":true,"release":"2018/11/30","genero":"Terror","titulo":"Cadáver","_id":{"$oid":"5bc7d0875d0e651b2e58cb99"},"año":"2019/02/21","sinopsis":"Un policía que acaba de salir de rehabilitación comienza a trabajar en una morgue del hospital de la ciudad. Poco a poco, irá descubriendo una serie de extraños y violentos sucesos causados por una entidad maligna que procede de uno de los cadáveres."}