{"autoSearch":true,"img":"https://image.tmdb.org/t/p/w600_and_h900_bestv2/62gIJdks9agqdYavMHJx3FlRXp9.jpg","imdb":"465086","servers":["https://allcalidad.la/la-maldicion-renace-allfp/","https://pelisgratis.live/the-grudge-g/","https://www.rexpelis.com/pelicula/la-maldicion-the-grudge","https://www.aquipelis.co/pelicula/la-maldicion-the-grudge/","https://www.pelisplay.co/pelicula/la-maldicion-the-grudge","https://www.cinetux.to/pelicula/la-maldicion-the-grudge/","https://fanpelis.net/la-maldicion-renace/","https://pelisplus.video/pelicula/la-maldicion-2020","https://pelisplus.video/pelicula/the-grudge","https://www.pelisxd.com/pelicula/la-maldicion-the-grudge/","https://www.pelispedia.mobi/pelicula/la-maldicion-the-grudge/","http://verpelisonline.tv/estrenos/11938-la-maldicion-the-grudge.html"],"isSaved":true,"release":"2020/01/02","genero":"Terror","titulo":"La Maldición (The Grudge)","_id":{"$oid":"ud9qjeocfiqn20ckqn1d0"},"año":"2020/03/21","sinopsis":"Después de que una joven madre asesina a su familia en su propia casa, una madre soltera y un detective intentan investigar y resolver el caso. Más tarde, descubren que la casa está maldita por un fantasma vengativo que condena a quienes entran con una muerte violenta."}