{"autoSearch":true,"img":"https://image.tmdb.org/t/p/w600_and_h900_bestv2/ma9gY6OikBev8MsMaeA6h2EIdGo.jpg","imdb":"476299","servers":["https://www.pelisplay.co/pelicula/pesadilla-en-el-infierno","https://allcalidad.la/pesadilla-en-el-infierno/","https://allpeliculas.io/pelicula/Pesadilla-en-el-infierno","https://pelisgratis.nu/ghostland/","https://www.aquipelis.info/pelicula/ghostland/","https://www.cinetux.to/pelicula/ver-pesadilla-en-el-infierno-ghostland-online/","https://www.pelisxd.com/pelicula/ghostland/","https://www.pelispedia.biz/pelicula/ghostland/","http://verpelisonline.tv/mas-vistas/1059-ghostland.html","https://www.repelisplus.vip/ver/ghostland/"],"isSaved":true,"release":"2018/03/15","genero":"Terror","titulo":"Ghostland","_id":{"$oid":"2124da70a08741788511d29c791feb66"},"año":"2018/03/15","sinopsis":"Una madre y sus dos hijos heredan una casa. Pero en su primera noche, aparecen unos asesinos y la madre se ve obligada a luchar para salvar a sus hijas."}