{"autoSearch":true,"img":"https://image.tmdb.org/t/p/w600_and_h900_bestv2/k3a41SS1q5xmbvzPvzTIfG7GDlp.jpg","imdb":"68735","servers":["https://www.pelisplay.tv/pelicula/warcraft-el-origen","https://www.inkapelis.tv/warcraft-completa-online-hd-1080p/","https://allcalidad.net/warcraft-el-origen/","https://allpeliculas.io/pelicula/Warcraft-El-primer-encuentro-de-dos-mundos","https://pelisgratis.live/warcraft-el-origen/","https://www.rexpelis.com/pelicula/warcraft-el-origen","https://www.aquipelis.co/pelicula/warcraft-el-origen/","https://v1.pelisplusgo.com/pelicula/warcraft-G6bs6"],"isSaved":true,"release":"2016/05/25","genero":"acción Aventura Fantasia ","titulo":"Warcraft: El origen","_id":{"$oid":"5bc7cff41f6e4f34af69efd2"},"año":"2016/06/3","sinopsis":"El pacífico reino de Azeroth está a punto de entrar en guerra para enfrentarse a unos terribles invasores: orcos guerreros que han dejado su destruido mundo para colonizar otro. Al abrirse un portal que conecta ambos mundos, un ejército se enfrenta a la destrucción, y el otro, a la extinción. Dos héroes, uno en cada bando, están a punto de chocar en un enfrentamiento que cambiará el destino de su familia, su pueblo y su hogar. Así empieza una espectacular saga de poder y sacrificio donde se descubren las numerosas caras de la guerra y donde cada uno lucha por lo suyo. Adaptación del popular videojuego homónimo."}