{"autoSearch":true,"img":"https://image.tmdb.org/t/p/w600_and_h900_bestv2/jBzPlhGrrSgQozGMzyoDPXUWdMt.jpg","imdb":"76757","servers":["https://www.pelisplay.co/pelicula/el-destino-de-jupiter","https://allcalidad.la/el-destino-de-jupiter/","https://pelisap.com/el-destino-de-jupiter-jupiter-ascending/","https://pelisplusgo.com/pelicula/jupiter-ascending-4OHx6","https://cinetux.nu/pelicula/ver-el-destino-de-jupiter-online-gratis-hd/","https://fanpelis.net/el-destino-de-jupiter/","https://pelisplus.video/pelicula/el-destino-de-jupiter","https://www.pelisxd.com/pelicula/el-destino-de-jupiter/","https://repelisgoo.net/pelicula/jupiter-ascending-AlUwL","http://verpelisonline.tv/action/481-el-destino-de-jupiter-2015.html"],"isSaved":true,"release":"2015/02/04","genero":"acción Aventura ","titulo":"El destino de Júpiter","_id":{"$oid":"5bc7d0bd5d0e651b2e58cc48"},"año":"2015/02/6","sinopsis":"La película se centrará en formas superiores de vida que nos vigilan desde otros mundos. Mila Kunis interpretará a Jupiter Jones, una inmigrante rusa que se dedica a fregar retretes para ganarse la vida. Pero la joven, ella sin saberlo, posee la misma composición genética que la Reina del Universo, por lo que será considerada como una amenaza para estos seres inmortales, que enviarán a un cazador ex militar, Caine (Channing Tatum), para dar con ella"}