{"autoSearch":true,"img":"https://image.tmdb.org/t/p/w600_and_h900_bestv2/4woGfb8TdZV1tMRInTAHo7OcxSP.jpg","imdb":"88042","servers":["https://allcalidad.la/abuelos-al-poder/","https://cinetux.nu/pelicula/ver-pelicula-abuelos-al-poder-parental-guidance-online-gratis-2012/","https://www.repelisplus.vip/ver/abuelos-al-poder/","https://fanpelis.net/s-0-s-familia-en-apuros/"],"isSaved":true,"release":"2012/12/25","genero":"Comedia Familiar ","titulo":"Abuelos al poder","_id":{"$oid":"5bc7d04b5d0e651b2e58cacd"},"año":"2012/12/25","sinopsis":"Artie y Diane Decker, un matrimonio en edad de jubilación que, tendrá que desempolvar el manual de cómo educar a los niños. Su hija, pide ayuda a Artie para que se encargue de sus tres hijos mientras ella permanece fuera de la ciudad por motivos de trabajo. Una propuesta a la que, por el bien de su relación, el abuelo no puede negarse.  El matrimonio pasará así unos días con sus nietos, intentando educarles lo mejor posible, aunque no será nada fácil. El estilo de vida que llevan, lleno de estrés por las tareas del colegio entran en conflicto con sus ideales y la casa pierde su anterior tranquilidad para siempre. Artie y Diane tendrán que aprender técnicas novedosas para aplicarse ellos mismos y poder así transmitírselas a sus nietos."}