{"tmdb":"38472","isSaved":true,"genero":"Accion","servidores":["https://www.pelisplay.tv/serie/ver-jessica-jones-online","https://www.pelisplus.to/serie/jessica-jones","https://fanpelis.net/series/marvel-jessica-jones","https://seriesblanco.org/capitulos/jessica-jones/","https://www.seriespapaya.nu/serie/jessica-jones.html","http://pelisplus.co/serie/jessica-jones/","https://www.repelisplus.vip/ver/marvels-jessica-jones-hd-d/"],"titulo":"Jessica Jones","enlace":"","_id":{"$oid":"5bca9c241f6e4f34af6f855e"},"poster":"https://image.tmdb.org/t/p/w600_and_h900_bestv2/wkFdanlAaV39sSXeslImfRUj3jQ.jpg","año":"2018/12/16","sinopsis":"Tras el trágico final de su breve carrera de superhéroe, Jessica Jones intenta reconstruir su vida como investigadora privada , tratando casos que involucran personas con habilidades extraordinarias en la ciudad de Nueva York ."}