{"tmdb":"60625","isSaved":true,"genero":"Animación Comedia","servidores":["https://www.pelisplay.tv/serie/rick-y-morty","https://fanpelis.net/series/rick-y-morty","https://seriesblanco.org/capitulos/rick-and-morty/","https://www.pelisplus.to/serie/rick-and-morty","https://www.seriespapaya.nu/serie/rick-and-morty.html","http://pelisplus.co/serie/rick-y-morty/","https://www.repelisplus.vip/ver/rick-and-morty-b/"],"titulo":"Rick y Morty","enlace":"","_id":{"$oid":"5bca8e1c1f6e4f34af6f7133"},"poster":"https://image.tmdb.org/t/p/w600_and_h900_bestv2/8kOWDBK6XlPUzckuHDo3wwVRFwt.jpg","año":"2018/09/30","sinopsis":"Comedia animada que narra las aventuras de un científico loco Rick Sánchez, que regresa después de 20 años para vivir con su hija, su marido y sus hijos Morty y Summer."}