{"tmdb":"71225","isSaved":true,"genero":"Drama","servidores":["https://www.pelisplay.tv/serie/las-chicas-del-cable","https://www.pelisplus.to/serie/las-chicas-del-cable","https://fanpelis.net/series/las-chicas-del-cable","https://seriesblanco.org/capitulos/las-chicas-del-cable/","https://www.seriespapaya.nu/serie/las-chicas-del-cable.html","http://pelisplus.co/serie/las-chicas-del-cable/","https://www.repelisplus.vip/ver/las-chicas-del-cable-e/"],"titulo":"Las Chicas Del Cable","enlace":"","_id":{"$oid":"5bca9c241f6e4f34af6f880e"},"poster":"https://image.tmdb.org/t/p/w600_and_h900_bestv2/2QZzVoZEHTZgj5KrhCHkcUr2ITU.jpg","año":"2019/01/30","sinopsis":"Madrid, año 1928. Las operadoras de la recién nacida Telefónica viven sus romances y envidias dentro de una empresa moderna, reflejo del cambio social de la época. Lidia, Marga, Ángeles y Carlota comienzan a trabajar como telefonistas en el edificio más moderno de toda la ciudad. Para ellas empieza la lucha por una independencia que tanto su entorno como la sociedad de entonces les niega. Su amistad será clave para conseguir sus sueños y juntas irán descubriendo lo que significa la verdadera libertad."}