{"tmdb":"89247","isSaved":true,"genero":"Accion","servidores":["https://www.pelisplay.tv/serie/ver-batwoman-online-001","https://fanpelis.net/series/batwoman","https://seriesblanco.org/capitulos/batwoman/","https://www.seriespapaya.nu/serie/batwoman.html","https://pelisplus.me/serie/batwoman/","https://www.repelisplus.vip/ver/batwoman/","https://pelisplushd.net/serie/batwoman"],"titulo":"Batwoman","enlace":"","_id":{"$oid":"5bca9c241f6e4f34af6f921e"},"poster":"https://image.tmdb.org/t/p/w600_and_h900_bestv2/jnaimWkIVSD9IInmZPyLYarSvvc.jpg","año":"2019/12/12","sinopsis":"'Batwoman' es una ficción que se centra en el personaje de Kate Kane, una mujer con pasión por la justicia social y talento para decir lo que piensa. Esta mujer decidida y luchadora salta a las calles de la ciudad de Gotham como Batwoman. Esto ocurre al ser expulsada del West Point por negarse a mentir sobre su sexualidad, Kate es homosexual. Armada de valor y coraje lucha contra el crimen de la ciudad que desea desesperadamente un salvador. Kate debe superar sus miedos antes de ser el símbolo de la esperanza de Gotham."}